easy_mcp_server/__init__.py
easy_mcp_server/server.py
easy_mcp_server/settings.py
easy_mcp_server-0.1.0.dist-info/licenses/LICENSE
easy_mcp_server-0.1.0.dist-info/METADATA
easy_mcp_server-0.1.0.dist-info/WHEEL
easy_mcp_server-0.1.0.dist-info/top_level.txt
easy_mcp_server-0.1.0.dist-info/RECORD
