Metadata-Version: 2.4
Name: easy-mcp-server
Version: 0.1.0
Summary: A simple MCP server with stdio or SSE transport
Author-email: Josh Wyatt <your@email.com>
License-Expression: MIT
Project-URL: Homepage, https://github.com/joshwyatt/easy-mcp-server
Project-URL: Bug Tracker, https://github.com/joshwyatt/easy-mcp-server/issues
Project-URL: Source Code, https://github.com/joshwyatt/easy-mcp-server
Requires-Python: >=3.11
License-File: LICENSE
Requires-Dist: fastapi>=0.95.0
Requires-Dist: uvicorn>=0.20.0
Requires-Dist: pydantic>=2.0.0
Requires-Dist: click>=8.0.0
Requires-Dist: mcp
Provides-Extra: dev
Requires-Dist: pytest>=7.0.0; extra == "dev"
Requires-Dist: pytest-cov>=4.0.0; extra == "dev"
Requires-Dist: sphinx<8.2.0,>=7.0.0; extra == "dev"
Requires-Dist: sphinx-rtd-theme>=1.3.0; extra == "dev"
Requires-Dist: sphinx-autodoc-typehints>=1.25.0; extra == "dev"
Requires-Dist: myst-parser>=2.0.0; extra == "dev"
Requires-Dist: build>=1.2.2.post1; extra == "dev"
Requires-Dist: twine>=6.1.0; extra == "dev"
Dynamic: license-file
